{"cameraMode":{"drawMode":0,"name":"Shaded","section":"Shading Mode"},"sceneLighting":true,"audioPlay":false,"sceneViewState":{"showFog":true,"showMaterialUpdate":false,"showSkybox":true,"showFlares":true,"showImageEffects":true,"showParticleSystems":true},"in2DMode":false,"pivot":{"x":-1.273971676826477,"y":-2.613990306854248,"z":7.419535160064697},"rotation":{"x":-0.02724813111126423,"y":-0.970320463180542,"z":0.20105238258838654,"w":-0.13150787353515626},"size":16.97420883178711,"orthographic":false}